utilsuneed/Utilities.py
utilsuneed/__init__.py
utilsuneed/idsonboard.py
utilsuneed/idsonground.py
utilsuneed-0.0.5.dist-info/LICENSE.txt
utilsuneed-0.0.5.dist-info/METADATA
utilsuneed-0.0.5.dist-info/WHEEL
utilsuneed-0.0.5.dist-info/top_level.txt
utilsuneed-0.0.5.dist-info/RECORD
