Metadata-Version: 2.1
Name: utilsuneed
Version: 0.0.5
Summary: A need for many
Home-page: UNKNOWN
Author: Paritosh Sapre
Author-email: paritoshsapre@gmail.com
License: UNKNOWN
Platform: UNKNOWN
Classifier: Programming Language :: Python :: 2
Classifier: License :: OSI Approved :: MIT License
Classifier: Operating System :: OS Independent
